Workbook

Sheet sales_transactions_raw
A1: deal_id | B1: deal_date | C1: month | D1: quarter | E1: rep_id | F1: rep_name | G1: region | H1: team | I1: product_id | J1: product_name | K1: category | L1: customer_segment | M1: segment_id | N1: channel | O1: quantity | P1: unit_price | Q1: discount_pct | R1: deal_value
A2: DL1000 | B2: 45297 | C2: 2024-01 | D2: Q1 | E2: REP001 | F2: Chukwuemeka Obi | G2: Lagos | H2: Enterprise | I2: PRD007 | J2: POS Terminal | K2: Hardware | L2: SME | M2: =INDEX( dim_segment!$A$2:$A$5,MATCH(L2, dim_segment!$B$2:$B$5, 0)) -> SEG002 | N2: Referral | O2: 4 | P2: 75000 | Q2: 0.08 | R2: 276000
A3: DL1001 | B3: 45304 | C3: 2024-01 | D3: Q1 | E3: REP001 | F3: Chukwuemeka Obi | G3: Lagos | H3: Enterprise | I3: PRD003 | J3: Data Backup Pro | K3: Cloud | L3: Enterprise | M3: =INDEX( dim_segment!$A$2:$A$5,MATCH(L3, dim_segment!$B$2:$B$5, 0)) -> SEG001 | N3: Inbound | O3: 1 | P3: 60000 | Q3: 0.09 | R3: 54600
A4: DL1002 | B4: 45310 | C4: 2024-01 | D4: Q1 | E4: REP001 | F4: Chukwuemeka Obi | G4: Lagos | H4: Enterprise | I4: PRD004 | J4: Cloud Hosting | K4: Cloud | L4: SME | M4: =INDEX( dim_segment!$A$2:$A$5,MATCH(L4, dim_segment!$B$2:$B$5, 0)) -> SEG002 | N4: Partner | O4: 4 | P4: 45000 | Q4: 0.16 | R4: 151200
A5: DL1003 | B5: 45313 | C5: 2024-01 | D5: Q1 | E5: REP001 | F5: Chukwuemeka Obi | G5: Lagos | H5: Enterprise | I5: PRD007 | J5: POS Terminal | K5: Hardware | L5: SME | M5: =INDEX( dim_segment!$A$2:$A$5,MATCH(L5, dim_segment!$B$2:$B$5, 0)) -> SEG002 | N5: Partner | O5: 2 | P5: 75000 | Q5: 0.07 | R5: 139500
A6: DL1004 | B6: 45294 | C6: 2024-01 | D6: Q1 | E6: REP001 | F6: Chukwuemeka Obi | G6: Lagos | H6: Enterprise | I6: PRD002 | J6: Payroll Manager | K6: Software | L6: Government | M6: =INDEX( dim_segment!$A$2:$A$5,MATCH(L6, dim_segment!$B$2:$B$5, 0)) -> SEG004 | N6: Partner | O6: 5 | P6: 85000 | Q6: 0.15 | R6: 361200
A7: DL1005 | B7: 45292 | C7: 2024-01 | D7: Q1 | E7: REP001 | F7: Chukwuemeka Obi | G7: Lagos | H7: Enterprise | I7: PRD007 | J7: POS Terminal | K7: Hardware | L7: Government | M7: =INDEX( dim_segment!$A$2:$A$5,MATCH(L7, dim_segment!$B$2:$B$5, 0)) -> SEG004 | N7: Referral | O7: 1 | P7: 75000 | Q7: 0.09 | R7: 68200
A8: DL1006 | B8: 45339 | C8: 2024-02 | D8: Q1 | E8: REP001 | F8: Chukwuemeka Obi | G8: Lagos | H8: Enterprise | I8: PRD006 | J8: Cybersecurity Pkg | K8: Services | L8: SME | M8: =INDEX( dim_segment!$A$2:$A$5,MATCH(L8, dim_segment!$B$2:$B$5, 0)) -> SEG002 | N8: Inbound | O8: 5 | P8: 200000 | Q8: 0.06 | R8: 940000
A9: DL1007 | B9: 45345 | C9: 2024-02 | D9: Q1 | E9: REP001 | F9: Chukwuemeka Obi | G9: Lagos | H9: Enterprise | I9: PRD001 | J9: CRM Suite | K9: Software | L9: SME | M9: =INDEX( dim_segment!$A$2:$A$5,MATCH(L9, dim_segment!$B$2:$B$5, 0)) -> SEG002 | N9: Inbound | O9: 3 | P9: 150000 | Q9: 0.07 | R9: 418500
A10: DL1008 | B10: 45324 | C10: 2024-02 | D10: Q1 | E10: REP001 | F10: Chukwuemeka Obi | G10: Lagos | H10: Enterprise | I10: PRD003 | J10: Data Backup Pro | K10: Cloud | L10: Enterprise | M10: =INDEX( dim_segment!$A$2:$A$5,MATCH(L10, dim_segment!$B$2:$B$5, 0)) -> SEG001 | N10: Direct | O10: 5 | P10: 60000 | Q10: 0.15 | R10: 255000
A11: DL1009 | B11: 45365 | C11: 2024-03 | D11: Q1 | E11: REP001 | F11: Chukwuemeka Obi | G11: Lagos | H11: Enterprise | I11: PRD003 | J11: Data Backup Pro | K11: Cloud | L11: Enterprise | M11: =INDEX( dim_segment!$A$2:$A$5,MATCH(L11, dim_segment!$B$2:$B$5, 0)) -> SEG001 | N11: Inbound | O11: 4 | P11: 60000 | Q11: 0.15 | R11: 204000
A12: DL1010 | B12: 45352 | C12: 2024-03 | D12: Q1 | E12: REP001 | F12: Chukwuemeka Obi | G12: Lagos | H12: Enterprise | I12: PRD002 | J12: Payroll Manager | K12: Software | L12: Government | M12: =INDEX( dim_segment!$A$2:$A$5,MATCH(L12, dim_segment!$B$2:$B$5, 0)) -> SEG004 | N12: Partner | O12: 2 | P12: 85000 | Q12: 0.1 | R12: 153000
A13: DL1011 | B13: 45377 | C13: 2024-03 | D13: Q1 | E13: REP001 | F13: Chukwuemeka Obi | G13: Lagos | H13: Enterprise | I13: PRD003 | J13: Data Backup Pro | K13: Cloud | L13: Enterprise | M13: =INDEX( dim_segment!$A$2:$A$5,MATCH(L13, dim_segment!$B$2:$B$5, 0)) -> SEG001 | N13: Referral | O13: 5 | P13: 60000 | Q13: 0.11 | R13: 267000
... A785: DL1783 | B785: 45634 | C785: 2024-12 | D785: Q4 | E785: REP012 | F785: Hauwa Musa | G785: Kano | H785: SME | I785: PRD005 | J785: IT Support Plan | K785: Services | L785: Enterprise | M785: =INDEX( dim_segment!$A$2:$A$5,MATCH(L785, dim_segment!$B$2:$B$5, 0)) -> SEG001 | N785: Partner | O785: 2 | P785: 120000 | Q785: 0.1 | R785: 216000

Sheet dim_rep
A1: rep_id | B1: rep_name | C1: region | D1: team
A2: REP001 | B2: Chukwuemeka Obi | C2: Lagos | D2: Enterprise
A3: REP002 | B3: Amina Bello | C3: Abuja | D3: SME
A4: REP003 | B4: Tunde Fashola | C4: Lagos | D4: Enterprise
A5: REP004 | B5: Ngozi Adeyemi | C5: Port Harcourt | D5: SME
A6: REP005 | B6: Emeka Nwosu | C6: Enugu | D6: SME
A7: REP006 | B7: Fatima Aliyu | C7: Kano | D7: SME
A8: REP007 | B8: Biodun Adeleke | C8: Ibadan | D8: SME
A9: REP008 | B9: Chisom Eze | C9: Port Harcourt | D9: Enterprise
A10: REP009 | B10: Rasheed Kareem | C10: Lagos | D10: Enterprise
A11: REP010 | B11: Yetunde Afolabi | C11: Abuja | D11: Enterprise
A12: REP011 | B12: Obinna Okafor | C12: Enugu | D12: SME
A13: REP012 | B13: Hauwa Musa | C13: Kano | D13: SME

Sheet dim_product
A1: product_id | B1: product_name | C1: category | D1: unit_price
A2: PRD001 | B2: CRM Suite | C2: Software | D2: 150000
A3: PRD002 | B3: Payroll Manager | C3: Software | D3: 85000
A4: PRD003 | B4: Data Backup Pro | C4: Cloud | D4: 60000
A5: PRD004 | B5: Cloud Hosting | C5: Cloud | D5: 45000
A6: PRD005 | B6: IT Support Plan | C6: Services | D6: 120000
A7: PRD006 | B7: Cybersecurity Pkg | C7: Services | D7: 200000
A8: PRD007 | B8: POS Terminal | C8: Hardware | D8: 75000
A9: PRD008 | B9: Network Setup | C9: Hardware | D9: 95000

Sheet dim_segment
A1: segment_id | B1: segment_name
A2: SEG001 | B2: Enterprise
A3: SEG002 | B3: SME
A4: SEG003 | B4: Startup
A5: SEG004 | B5: Government

Sheet dim_date
A1: Date_key | B1: day | C1: month_no | D1: month_name | E1: quarter | F1: quarter_no | G1: year | H1: year_month | I1: day_name | J1: is_weekend
A2: 45292 | B2: =DAY(A2) -> 1 | C2: =MONTH(A2) -> 1 | D2: =TEXT(A2,"MMM") -> Jan | E2: ="Q"&ROUNDUP(MONTH(A2)/3,0) -> Q1 | F2: =ROUNDUP(MONTH(A2)/3,0) -> 1 | G2: =YEAR(A2) -> 2024 | H2: =TEXT(A2,"YYYY-MMM") -> 2024-Jan | I2: =TEXT(A2,"DDD") -> Mon | J2: =IF(WEEKDAY(A2,2)>=6,"Weekend","Weekday") -> Weekday
A3: =A2+1 -> 45293 | B3: =DAY(A3) -> 2 | C3: =MONTH(A3) -> 1 | D3: =TEXT(A3,"MMM") -> Jan | E3: ="Q"&ROUNDUP(MONTH(A3)/3,0) -> Q1 | F3: =ROUNDUP(MONTH(A3)/3,0) -> 1 | G3: =YEAR(A3) -> 2024 | H3: =TEXT(A3,"YYYY-MMM") -> 2024-Jan | I3: =TEXT(A3,"DDD") -> Tue | J3: =IF(WEEKDAY(A3,2)>=6,"Weekend","Weekday") -> Weekday
A4: =A3+1 -> 45294 | B4: =DAY(A4) -> 3 | C4: =MONTH(A4) -> 1 | D4: =TEXT(A4,"MMM") -> Jan | E4: ="Q"&ROUNDUP(MONTH(A4)/3,0) -> Q1 | F4: =ROUNDUP(MONTH(A4)/3,0) -> 1 | G4: =YEAR(A4) -> 2024 | H4: =TEXT(A4,"YYYY-MMM") -> 2024-Jan | I4: =TEXT(A4,"DDD") -> Wed | J4: =IF(WEEKDAY(A4,2)>=6,"Weekend","Weekday") -> Weekday
A5: =A4+1 -> 45295 | B5: =DAY(A5) -> 4 | C5: =MONTH(A5) -> 1 | D5: =TEXT(A5,"MMM") -> Jan | E5: ="Q"&ROUNDUP(MONTH(A5)/3,0) -> Q1 | F5: =ROUNDUP(MONTH(A5)/3,0) -> 1 | G5: =YEAR(A5) -> 2024 | H5: =TEXT(A5,"YYYY-MMM") -> 2024-Jan | I5: =TEXT(A5,"DDD") -> Thu | J5: =IF(WEEKDAY(A5,2)>=6,"Weekend","Weekday") -> Weekday
A6: =A5+1 -> 45296 | B6: =DAY(A6) -> 5 | C6: =MONTH(A6) -> 1 | D6: =TEXT(A6,"MMM") -> Jan | E6: ="Q"&ROUNDUP(MONTH(A6)/3,0) -> Q1 | F6: =ROUNDUP(MONTH(A6)/3,0) -> 1 | G6: =YEAR(A6) -> 2024 | H6: =TEXT(A6,"YYYY-MMM") -> 2024-Jan | I6: =TEXT(A6,"DDD") -> Fri | J6: =IF(WEEKDAY(A6,2)>=6,"Weekend","Weekday") -> Weekday
A7: =A6+1 -> 45297 | B7: =DAY(A7) -> 6 | C7: =MONTH(A7) -> 1 | D7: =TEXT(A7,"MMM") -> Jan | E7: ="Q"&ROUNDUP(MONTH(A7)/3,0) -> Q1 | F7: =ROUNDUP(MONTH(A7)/3,0) -> 1 | G7: =YEAR(A7) -> 2024 | H7: =TEXT(A7,"YYYY-MMM") -> 2024-Jan | I7: =TEXT(A7,"DDD") -> Sat | J7: =IF(WEEKDAY(A7,2)>=6,"Weekend","Weekday") -> Weekend
A8: =A7+1 -> 45298 | B8: =DAY(A8) -> 7 | C8: =MONTH(A8) -> 1 | D8: =TEXT(A8,"MMM") -> Jan | E8: ="Q"&ROUNDUP(MONTH(A8)/3,0) -> Q1 | F8: =ROUNDUP(MONTH(A8)/3,0) -> 1 | G8: =YEAR(A8) -> 2024 | H8: =TEXT(A8,"YYYY-MMM") -> 2024-Jan | I8: =TEXT(A8,"DDD") -> Sun | J8: =IF(WEEKDAY(A8,2)>=6,"Weekend","Weekday") -> Weekend
A9: =A8+1 -> 45299 | B9: =DAY(A9) -> 8 | C9: =MONTH(A9) -> 1 | D9: =TEXT(A9,"MMM") -> Jan | E9: ="Q"&ROUNDUP(MONTH(A9)/3,0) -> Q1 | F9: =ROUNDUP(MONTH(A9)/3,0) -> 1 | G9: =YEAR(A9) -> 2024 | H9: =TEXT(A9,"YYYY-MMM") -> 2024-Jan | I9: =TEXT(A9,"DDD") -> Mon | J9: =IF(WEEKDAY(A9,2)>=6,"Weekend","Weekday") -> Weekday
A10: =A9+1 -> 45300 | B10: =DAY(A10) -> 9 | C10: =MONTH(A10) -> 1 | D10: =TEXT(A10,"MMM") -> Jan | E10: ="Q"&ROUNDUP(MONTH(A10)/3,0) -> Q1 | F10: =ROUNDUP(MONTH(A10)/3,0) -> 1 | G10: =YEAR(A10) -> 2024 | H10: =TEXT(A10,"YYYY-MMM") -> 2024-Jan | I10: =TEXT(A10,"DDD") -> Tue | J10: =IF(WEEKDAY(A10,2)>=6,"Weekend","Weekday") -> Weekday
A11: =A10+1 -> 45301 | B11: =DAY(A11) -> 10 | C11: =MONTH(A11) -> 1 | D11: =TEXT(A11,"MMM") -> Jan | E11: ="Q"&ROUNDUP(MONTH(A11)/3,0) -> Q1 | F11: =ROUNDUP(MONTH(A11)/3,0) -> 1 | G11: =YEAR(A11) -> 2024 | H11: =TEXT(A11,"YYYY-MMM") -> 2024-Jan | I11: =TEXT(A11,"DDD") -> Wed | J11: =IF(WEEKDAY(A11,2)>=6,"Weekend","Weekday") -> Weekday
A12: =A11+1 -> 45302 | B12: =DAY(A12) -> 11 | C12: =MONTH(A12) -> 1 | D12: =TEXT(A12,"MMM") -> Jan | E12: ="Q"&ROUNDUP(MONTH(A12)/3,0) -> Q1 | F12: =ROUNDUP(MONTH(A12)/3,0) -> 1 | G12: =YEAR(A12) -> 2024 | H12: =TEXT(A12,"YYYY-MMM") -> 2024-Jan | I12: =TEXT(A12,"DDD") -> Thu | J12: =IF(WEEKDAY(A12,2)>=6,"Weekend","Weekday") -> Weekday
A13: =A12+1 -> 45303 | B13: =DAY(A13) -> 12 | C13: =MONTH(A13) -> 1 | D13: =TEXT(A13,"MMM") -> Jan | E13: ="Q"&ROUNDUP(MONTH(A13)/3,0) -> Q1 | F13: =ROUNDUP(MONTH(A13)/3,0) -> 1 | G13: =YEAR(A13) -> 2024 | H13: =TEXT(A13,"YYYY-MMM") -> 2024-Jan | I13: =TEXT(A13,"DDD") -> Fri | J13: =IF(WEEKDAY(A13,2)>=6,"Weekend","Weekday") -> Weekday
A14: =A13+1 -> 45304 | B14: =DAY(A14) -> 13 | C14: =MONTH(A14) -> 1 | D14: =TEXT(A14,"MMM") -> Jan | E14: ="Q"&ROUNDUP(MONTH(A14)/3,0) -> Q1 | F14: =ROUNDUP(MONTH(A14)/3,0) -> 1 | G14: =YEAR(A14) -> 2024 | H14: =TEXT(A14,"YYYY-MMM") -> 2024-Jan | I14: =TEXT(A14,"DDD") -> Sat | J14: =IF(WEEKDAY(A14,2)>=6,"Weekend","Weekday") -> Weekend
... A367: =A366+1 -> 45657 | B367: =DAY(A367) -> 31 | C367: =MONTH(A367) -> 12 | D367: =TEXT(A367,"MMM") -> Dec | E367: ="Q"&ROUNDUP(MONTH(A367)/3,0) -> Q4 | F367: =ROUNDUP(MONTH(A367)/3,0) -> 4 | G367: =YEAR(A367) -> 2024 | H367: =TEXT(A367,"YYYY-MMM") -> 2024-Dec | I367: =TEXT(A367,"DDD") -> Tue | J367: =IF(WEEKDAY(A367,2)>=6,"Weekend","Weekday") -> Weekday

Sheet dim_month
A1: year_month | B1: month_name | C1: month_no | D1: quarter | E1: quarter_no | F1: year
A2: 2024-01 | B2: Jan | C2: 1 | D2: Q1 | E2: 1 | F2: 2024
A3: 2024-02 | B3: Feb | C3: 2 | D3: Q2 | E3: 1 | F3: 2024
A4: 2024-03 | B4: Mar | C4: 3 | D4: Q3 | E4: 1 | F4: 2024
A5: 2024-04 | B5: Apr | C5: 4 | D5: Q2 | E5: 2 | F5: 2024
A6: 2024-05 | B6: May | C6: 5 | D6: Q2 | E6: 2 | F6: 2024
A7: 2024-06 | B7: Jun | C7: 6 | D7: Q2 | E7: 2 | F7: 2024
A8: 2024-07 | B8: Jul | C8: 7 | D8: Q3 | E8: 3 | F8: 2024
A9: 2024-08 | B9: Aug | C9: 8 | D9: Q3 | E9: 3 | F9: 2024
A10: 2024-09 | B10: Sep | C10: 9 | D10: Q3 | E10: 3 | F10: 2024
A11: 2024-10 | B11: Oct | C11: 10 | D11: Q4 | E11: 4 | F11: 2024
A12: 2024-11 | B12: Nov | C12: 11 | D12: Q4 | E12: 4 | F12: 2024
A13: 2024-12 | B13: Dec | C13: 12 | D13: Q4 | E13: 4 | F13: 2024

Sheet Fact_sales
A1: deal_id | B1: deal_date | C1: rep_id | D1: product_id | E1: segment_id | F1: channel | G1: quantity | H1: unit_price | I1: discount_pct | J1: deal_value
A2: DL1000 | B2: 45297 | C2: REP001 | D2: PRD007 | E2: SEG002 | F2: Referral | G2: 4 | H2: 75000 | I2: 0.08 | J2: 276000
A3: DL1001 | B3: 45304 | C3: REP001 | D3: PRD003 | E3: SEG001 | F3: Inbound | G3: 1 | H3: 60000 | I3: 0.09 | J3: 54600
A4: DL1002 | B4: 45310 | C4: REP001 | D4: PRD004 | E4: SEG002 | F4: Partner | G4: 4 | H4: 45000 | I4: 0.16 | J4: 151200
A5: DL1003 | B5: 45313 | C5: REP001 | D5: PRD007 | E5: SEG002 | F5: Partner | G5: 2 | H5: 75000 | I5: 0.07 | J5: 139500
A6: DL1004 | B6: 45294 | C6: REP001 | D6: PRD002 | E6: SEG004 | F6: Partner | G6: 5 | H6: 85000 | I6: 0.15 | J6: 361200
A7: DL1005 | B7: 45292 | C7: REP001 | D7: PRD007 | E7: SEG004 | F7: Referral | G7: 1 | H7: 75000 | I7: 0.09 | J7: 68200
A8: DL1006 | B8: 45339 | C8: REP001 | D8: PRD006 | E8: SEG002 | F8: Inbound | G8: 5 | H8: 200000 | I8: 0.06 | J8: 940000
A9: DL1007 | B9: 45345 | C9: REP001 | D9: PRD001 | E9: SEG002 | F9: Inbound | G9: 3 | H9: 150000 | I9: 0.07 | J9: 418500
A10: DL1008 | B10: 45324 | C10: REP001 | D10: PRD003 | E10: SEG001 | F10: Direct | G10: 5 | H10: 60000 | I10: 0.15 | J10: 255000
A11: DL1009 | B11: 45365 | C11: REP001 | D11: PRD003 | E11: SEG001 | F11: Inbound | G11: 4 | H11: 60000 | I11: 0.15 | J11: 204000
A12: DL1010 | B12: 45352 | C12: REP001 | D12: PRD002 | E12: SEG004 | F12: Partner | G12: 2 | H12: 85000 | I12: 0.1 | J12: 153000
A13: DL1011 | B13: 45377 | C13: REP001 | D13: PRD003 | E13: SEG001 | F13: Referral | G13: 5 | H13: 60000 | I13: 0.11 | J13: 267000
... A785: DL1783 | B785: 45634 | C785: REP012 | D785: PRD005 | E785: SEG001 | F785: Partner | G785: 2 | H785: 120000 | I785: 0.1 | J785: 216000
